{
  "_info": "this file contains a list of all trusted peers and can be shared",
  "knownPeers": [
    {
      "endpoint": {
        "host": "85.25.36.97",
        "port": 7890,
        "protocol": "http"
      },
      "identity": {
        "name": "alice2",
        "public-key": "3302e7703ee9f364c25bbfebb9c12ac91fa9dcd69e09a5d4f3830d71505a2350"
      }
    },
    {
      "endpoint": {
        "host": "85.25.36.92",
        "port": 7890,
        "protocol": "http"
      },
      "identity": {
        "name": "alice3",
        "public-key": "708fbae6f7dc43b19e18a783d99535650504b60abd27b12137d17227ee3d5e84"
      }
    },
    {
      "endpoint": {
        "host": "199.217.112.135",
        "port": 7890,
        "protocol": "http"
      },
      "identity": {
        "name": "alice4",
        "public-key": "c7e68c147fe246caaf6f09d3a1b54a5744b1d3f55a22a8557c3a063d70669262"
      }
    },
    {
      "endpoint": {
        "host": "108.61.182.27",
        "port": 7890,
        "protocol": "http"
      },
      "identity": {
        "name": "alice5",
        "public-key": "c1d806564c3dda901c46e1dd4b533aae28eac148672afd69c91e7b51fe930948"
      }
    },
    {
      "endpoint": {
        "host": "108.61.168.86",
        "port": 7890,
        "protocol": "http"
      },
      "identity": {
        "name": "alice6",
        "public-key": "266c29aefaa4dbd3c206ea235c079d791dbb9808c428d4b3b206a088523ed1c8"
      }
    },
    {
      "endpoint": {
        "host": "san.nem.ninja",
        "port": 7890,
        "protocol": "http"
      },
      "identity": {
        "name": "[color=#dfa82f]s[/color][color=#8e8e8e]a[color][color=#41ce7b]n[/color]",
        "public-key": "4a25bf65646c8c3df87179bcb5ff7c4c3176ea02153a82d14615d53cf448ed83"
      }
    },
    {
      "endpoint": {
        "host": "go.nem.ninja",
        "port": 7890,
        "protocol": "http"
      },
      "identity": {
        "name": "[color=#41ce7b]g[/color][color=#dfa82f]o[color]",
        "public-key": "f973d58cd550da293e52764d431edd5a04b28baa2b7b83b2e8fb7a5d3a7c398b"
      }
    },
    {
      "endpoint": {
        "host": "hachi.nem.ninja",
        "port": 7890,
        "protocol": "http"
      },
      "identity": {
        "name": "[color=#41ce7b]h[/color][color=#8e8e8e]ac[color][color=#41ce7b]hi[/color]",
        "public-key": "09ae29b40e95d4d65a4b4e65fa4582c0c4040ed15a0cabba4bf50f4c76287844"
      }
    },
    {
      "endpoint": {
        "host": "jusan.nem.ninja",
        "port": 7890,
        "protocol": "http"
      },
      "identity": {
        "name": "[color=#dfa82f]ju[/color][color=#8e8e8e]s[color][color=#41ce7b]an[/color]",
        "public-key": "1cf373a7391bd179865904dfb6e6e4a427927ac90530b0396ad69392863e1b52"
      }
    },
    {
      "endpoint": {
        "host": "nijuichi.nem.ninja",
        "port": 7890,
        "protocol": "http"
      },
      "identity": {
        "name": "[color=#dfa82f]ni[/color][color=#8e8e8e]ju[color][color=#41ce7b]ichi[/color]",
        "public-key": "9c95a96be8a319d77eb71dec3c841afc687d1b039007813fd83a10fabcdb21f7"
      }
    },
    {
      "endpoint": {
        "protocol": "http",
        "port": 7890,
        "host": "108.61.223.23"
      },
      "identity": {
        "name": "makoto",
        "public-key": "a18b9cdf30a85868d74772985f322aa20b5fe601626c43077ba1351579f66dab"
      }
    }
  ]
}
